retag_opus/__init__.py
retag_opus/__main__.py
retag_opus/app.py
retag_opus/cli.py
retag_opus/colors.py
retag_opus/constants.py
retag_opus/description_parser.py
retag_opus/exceptions.py
retag_opus/music_tags.py
retag_opus/tags_parser.py
retag_opus/utils.py
retag_opus-0.4.1.dist-info/LICENSE
retag_opus-0.4.1.dist-info/METADATA
retag_opus-0.4.1.dist-info/WHEEL
retag_opus-0.4.1.dist-info/entry_points.txt
retag_opus-0.4.1.dist-info/RECORD
