Metadata-Version: 2.1
Name: retag_opus
Version: 0.4.1
Summary: An app to tag music files downloaded from Youtube with all the information available in the Youtube description.
License: GPL-3.0-or-later
Author: Simon Bengtsson
Author-email: gevhaz@tutanota.com
Requires-Python: >=3.10,<4.0
Classifier: License :: OSI Approved :: GNU General Public License v3 or later (GPLv3+)
Classifier: Programming Language :: Python :: 3
Classifier: Programming Language :: Python :: 3.10
Classifier: Programming Language :: Python :: 3.11
Classifier: Programming Language :: Python :: 3.12
Requires-Dist: colorama (>=0.4.4,<0.5.0)
Requires-Dist: mutagen (>=1.45.1,<2.0.0)
Requires-Dist: shtab (>=1.5.4,<2.0.0)
Requires-Dist: simple-term-menu (>=1.4.1,<2.0.0)
